extsorter/__init__.py
extsorter/core.py
extsorter-0.1.4.dist-info/WHEEL
extsorter-0.1.4.dist-info/entry_points.txt
extsorter-0.1.4.dist-info/METADATA
extsorter-0.1.4.dist-info/RECORD
